MANIFEST.in
README.md
setup.py
sensenet/__init__.py
sensenet/configuration.py
sensenet/core.py
sensenet/error.py
sensenet/version.py
sensenet.egg-info/PKG-INFO
sensenet.egg-info/SOURCES.txt
sensenet.egg-info/dependency_links.txt
sensenet.egg-info/not-zip-safe
sensenet.egg-info/requires.txt
sensenet.egg-info/top_level.txt
sensenet/envs/__init__.py
sensenet/envs/registration.py
sensenet/envs/handroid/__init__.py
sensenet/envs/handroid/blank_env.py
sensenet/envs/handroid/exp_hand_env.py
sensenet/envs/handroid/hand_env.py
sensenet/envs/handroid/index_finger_hand_env.py
sensenet/envs/handroid/index_finger_only_hand_env.py
sensenet/envs/handroid/survive_env.py
sensenet/envs/handroid/touch_wand_env.py
sensenet/envs/handroid/data/circle.stl
sensenet/envs/handroid/data/key.stl
sensenet/envs/handroid/data/loader.obj.urdf
sensenet/envs/handroid/data/loader.stl.urdf
sensenet/envs/handroid/data/mesh.urdf
sensenet/envs/handroid/data/missile.obj
sensenet/envs/handroid/data/pyramid.stl
sensenet/envs/handroid/data/MPL/LICENSE.txt
sensenet/envs/handroid/data/MPL/MPL.xml
sensenet/envs/handroid/data/MPL/MPL_index_only.xml
sensenet/envs/handroid/data/MPL/mpl2.xml
sensenet/envs/handroid/data/MPL/mesh/index0.stl
sensenet/envs/handroid/data/MPL/mesh/index0_collision.stl
sensenet/envs/handroid/data/MPL/mesh/index1.stl
sensenet/envs/handroid/data/MPL/mesh/index1_collision.stl
sensenet/envs/handroid/data/MPL/mesh/index2.stl
sensenet/envs/handroid/data/MPL/mesh/index2_collision.stl
sensenet/envs/handroid/data/MPL/mesh/index3.stl
sensenet/envs/handroid/data/MPL/mesh/index3_collision.stl
sensenet/envs/handroid/data/MPL/mesh/middle0.stl
sensenet/envs/handroid/data/MPL/mesh/middle0_collision.stl
sensenet/envs/handroid/data/MPL/mesh/middle1.stl
sensenet/envs/handroid/data/MPL/mesh/middle1_collision.stl
sensenet/envs/handroid/data/MPL/mesh/middle2.stl
sensenet/envs/handroid/data/MPL/mesh/middle2_collision.stl
sensenet/envs/handroid/data/MPL/mesh/middle3.stl
sensenet/envs/handroid/data/MPL/mesh/middle3_collision.stl
sensenet/envs/handroid/data/MPL/mesh/palm.stl
sensenet/envs/handroid/data/MPL/mesh/palm_collision.stl
sensenet/envs/handroid/data/MPL/mesh/pinky0.stl
