Metadata-Version: 1.0
Name: sensenet
Version: 0.0.22
Summary: SenseNet
Home-page: https://github.com/jtoy/sensenet
Author: Jason Toy
Author-email: support@sensenet.ai
License: UNKNOWN
Keywords: deep learning,reinforcement learning,machine learning,robotics
Platform: UNKNOWN
